{"Player1Move":{"SuccessfulMove":true,"CommandIssued":"FireSingleShot","CenterPoint":"5, 0","ShieldRadius":0,"PlaceShipString":"Battleship 3 1 East ,Carrier 2 6 East ,Cruiser 0 3 north ,Destroyer 5 3 East ,Submarine 2 2 north ","Energy":8,"RemainingShieldTurns":0},"Player2Move":{"SuccessfulMove":true,"CommandIssued":"FireSingleShot","CenterPoint":"2, 4","ShieldRadius":0,"PlaceShipString":"Battleship 3 1 East ,Carrier 2 6 East ,Cruiser 0 3 north ,Destroyer 5 3 East ,Submarine 2 2 north ","Energy":8,"RemainingShieldTurns":0}}